zonic/__init__.py
zonic/configuration.py
zonic/constants.py
zonic/exceptions.py
zonic/instance.py
zonic/zonic.py
zonic/abc/base_classes.py
zonic/impl/__init__.py
zonic/impl/attacker.py
zonic/impl/scanner.py
zonic/impl/writer.py
zonic/utility/argparsing.py
zonic/utility/string_utils.py
zonic-0.1.7.dist-info/AUTHORS.rst
zonic-0.1.7.dist-info/LICENSE
zonic-0.1.7.dist-info/METADATA
zonic-0.1.7.dist-info/WHEEL
zonic-0.1.7.dist-info/entry_points.txt
zonic-0.1.7.dist-info/top_level.txt
zonic-0.1.7.dist-info/RECORD
